llamazure/rid/__init__.py
llamazure/rid/conv.py
llamazure/rid/mp.py
llamazure/rid/rid.py
llamazure/rid/util.py
llamazure.rid-0.1.0.dist-info/METADATA
llamazure.rid-0.1.0.dist-info/WHEEL
llamazure.rid-0.1.0.dist-info/namespace_packages.txt
llamazure.rid-0.1.0.dist-info/top_level.txt
llamazure.rid-0.1.0.dist-info/RECORD
